{
  "id": "1676247639263395_487051410102546",
  "created_time": "2022-09-30T12:36:13+0000",
  "permalink_url": "https://www.facebook.com/1525148926292784/posts/487051410102546",
  "media_type": "link",
  "images": 1,
  "attachments": [
    {
      "media_type": "link",
      "type": "share",
      "url": "https://www.ptt.cc/bbs/C_Chat/M.1664478425.A.D14.html",
      "title": "[閒聊] AI畫的古典風大屁屁",
      "description": "大屁屁 https://i.imgur.com/mkadCIs.jpg 大屁屁2 https://i.imgur.com/4iRNIkl.jpg 貓耳+大奶"
    }
  ]
}
